CHANGES.txt
LICENSE.txt
MANIFEST.in
README.txt
distribute_setup.py
setup.py
docs/build/html/_sources/index.txt
openjub_py/__init__.py
openjub_py.egg-info/PKG-INFO
openjub_py.egg-info/SOURCES.txt
openjub_py.egg-info/dependency_links.txt
openjub_py.egg-info/requires.txt
openjub_py.egg-info/top_level.txt