Metadata-Version: 1.0
Name: openjub-py
Version: 0.1
Summary: A Python Client for OpenJUB. 
Home-page: https://github.com/tkw1536/openjub_py
Author: Tom Wiesing
Author-email: tkw01536@gmail.com
License: See LICENSE.txt
Platform: UNKNOWN
